Memory/src/bit_extender.sv
module bit_extender #(parameter WIDTH = 32, IMM_WIDTH = 16)(
    input logic ExtOp,
    input logic[IMM_WIDTH-1:0] immediate_var,
    output logic[WIDTH-1:0] extended_var
);


always_comb begin : bit_extender
    if(ExtOp == 0) begin
        extended_var[WIDTH-1:IMM_WIDTH] = {(WIDTH-IMM_WIDTH){immediate_var[IMM_WIDTH-1]}};
        extended_var[IMM_WIDTH-1:0]=immediate_var;
    end
    else begin
        extended_var[WIDTH-1:IMM_WIDTH] = '0;
        extended_var[IMM_WIDTH-1:0] = immediate_var;
    end

end
endmodule

Memory/tb/bit_extender_tb.sv
module bit_extender_tb;
localparam WIDTH     = 32;
localparam IMM_WIDTH = 16;

logic                    ExtOp;
logic [IMM_WIDTH-1:0]    immediate_var;
logic [WIDTH-1:0]        extended_var;

bit_extender #(.WIDTH(WIDTH), .IMM_WIDTH(IMM_WIDTH)) dut (
    .ExtOp(ExtOp),
    .immediate_var(immediate_var),
    .extended_var(extended_var)
);

task check(
    input logic [WIDTH-1:0] expected,
    input string            label
);
    #5;
    if (extended_var === expected)
        $display("PASS [%s] ExtOp=%b imm=%h | extended=%h", label, ExtOp, immediate_var, extended_var);
    else
        $error("FAIL [%s] ExtOp=%b imm=%h | expected=%h got=%h", label, ExtOp, immediate_var, expected, extended_var);
endtask

initial begin
    $dumpfile("dump/bit_extender.vcd");
    $dumpvars(0, bit_extender_tb);

    // ── Sign extend (ExtOp = 0) ───────────────────────────────────────
    ExtOp = 1'b0;
    immediate_var = 16'h0000; check(32'h00000000, "sign-extend zero");
    immediate_var = 16'hFFFF; check(32'hFFFFFFFF, "sign-extend all ones");
    immediate_var = 16'h8000; check(32'hFFFF8000, "sign-extend negative MSB set");
    immediate_var = 16'h7FFF; check(32'h00007FFF, "sign-extend max positive");
    immediate_var = 16'h0001; check(32'h00000001, "sign-extend positive one");
    immediate_var = 16'hABCD; check(32'hFFFFABCD, "sign-extend negative pattern");
    for (int i = 0; i < 20; i++) begin
        immediate_var = $urandom;
        check({{16{immediate_var[15]}}, immediate_var}, "sign-extend random");
    end

    // ── Zero extend (ExtOp = 1) ───────────────────────────────────────
    ExtOp = 1'b1;
    immediate_var = 16'h0000; check(32'h00000000, "zero-extend zero");
    immediate_var = 16'hFFFF; check(32'h0000FFFF, "zero-extend all ones");
    immediate_var = 16'h8000; check(32'h00008000, "zero-extend MSB set");
    immediate_var = 16'hABCD; check(32'h0000ABCD, "zero-extend pattern");
    for (int i = 0; i < 20; i++) begin
        immediate_var = $urandom;
        check({16'h0000, immediate_var}, "zero-extend random");
    end

    $display("All bit_extender tests complete");
    $finish;
end
endmodule

Memory/dump/bit_extender.vcd
$date
	Thu Jul 30 12:49:50 2026
$end
$version
	Icarus Verilog
$end
$timescale
	1s
$end
$scope module bit_extender_tb $end
$var wire 32 ! extended_var [31:0] $end
$var parameter 32 " IMM_WIDTH $end
$var parameter 32 # WIDTH $end
$var reg 1 $ ExtOp $end
$var reg 16 % immediate_var [15:0] $end
$scope module dut $end
$var wire 1 $ ExtOp $end
$var wire 16 & immediate_var [15:0] $end
$var parameter 32 ' IMM_WIDTH $end
$var parameter 32 ( WIDTH $end
$var reg 32 ) extended_var [31:0] $end
$scope begin bit_extender $end
$upscope $end
$upscope $end
$scope begin $ivl_for_loop0 $end
$var integer 32 * i [31:0] $end
$upscope $end
$scope begin $ivl_for_loop1 $end
$var integer 32 + i [31:0] $end
$upscope $end
$scope task check $end
$var reg 32 , expected [31:0] $end
$upscope $end
$upscope $end
$enddefinitions $end
$comment Show the parameter values. $end
$dumpall
b100000 (
b10000 '
b100000 #
b10000 "
$end
#0
$dumpvars
b0 ,
b0 +
b0 *
b0 )
b0 &
b0 %
0$
b0 !
$end
#5
b11111111111111111111111111111111 !
b11111111111111111111111111111111 )
b11111111111111111111111111111111 ,
b1111111111111111 %
b1111111111111111 &
#10
b11111111111111111000000000000000 !
b11111111111111111000000000000000 )
b11111111111111111000000000000000 ,
b1000000000000000 %
b1000000000000000 &
#15
b111111111111111 !
b111111111111111 )
b111111111111111 ,
b111111111111111 %
b111111111111111 &
#20
b1 !
b1 )
b1 ,
b1 %
b1 &
#25
b11111111111111111010101111001101 !
b11111111111111111010101111001101 )
b11111111111111111010101111001101 ,
b1010101111001101 %
b1010101111001101 &
#30
b11010100100100 !
b11010100100100 )
b11010100100100 ,
b11010100100100 %
b11010100100100 &
#35
b101111010000001 !
b101111010000001 )
b101111010000001 ,
b101111010000001 %
b101111010000001 &
b1 *
#40
b11111111111111111101011000001001 !
b11111111111111111101011000001001 )
b11111111111111111101011000001001 ,
b1101011000001001 %
b1101011000001001 &
b10 *
#45
b101011001100011 !
b101011001100011 )
b101011001100011 ,
b101011001100011 %
b101011001100011 &
b11 *
#50
b111101100001101 !
b111101100001101 )
b111101100001101 ,
b111101100001101 %
b111101100001101 &
b100 *
#55
b11111111111111111001100110001101 !
b11111111111111111001100110001101 )
b11111111111111111001100110001101 ,
b1001100110001101 %
b1001100110001101 &
b101 *
#60
b11111111111111111000010001100101 !
b11111111111111111000010001100101 )
b11111111111111111000010001100101 ,
b1000010001100101 %
b1000010001100101 &
b110 *
#65
b101001000010010 !
b101001000010010 )
b101001000010010 ,
b101001000010010 %
b101001000010010 &
b111 *
#70
b11111111111111111110001100000001 !
b11111111111111111110001100000001 )
b11111111111111111110001100000001 ,
b1110001100000001 %
b1110001100000001 &
b1000 *
#75
b11111111111111111100110100001101 !
b11111111111111111100110100001101 )
b11111111111111111100110100001101 ,
b1100110100001101 %
b1100110100001101 &
b1001 *
#80
b11111111111111111111000101110110 !
b11111111111111111111000101110110 )
b11111111111111111111000101110110 ,
b1111000101110110 %
b1111000101110110 &
b1010 *
#85
b11111111111111111100110100111101 !
b11111111111111111100110100111101 )
b11111111111111111100110100111101 ,
b1100110100111101 %
b1100110100111101 &
b1011 *
#90
b101011111101101 !
b101011111101101 )
b101011111101101 ,
b101011111101101 %
b101011111101101 &
b1100 *
#95
b11111111111111111111011110001100 !
b11111111111111111111011110001100 )
b11111111111111111111011110001100 ,
b1111011110001100 %
b1111011110001100 &
b1101 *
#100
b11111111111111111110100111111001 !
b11111111111111111110100111111001 )
b11111111111111111110100111111001 ,
b1110100111111001 %
b1110100111111001 &
b1110 *
#105
b10010011000110 !
b10010011000110 )
b10010011000110 ,
b10010011000110 %
b10010011000110 &
b1111 *
#110
b11111111111111111000010011000101 !
b11111111111111111000010011000101 )
b11111111111111111000010011000101 ,
b1000010011000101 %
b1000010011000101 &
b10000 *
#115
b11111111111111111101001010101010 !
b11111111111111111101001010101010 )
b11111111111111111101001010101010 ,
b1101001010101010 %
b1101001010101010 &
b10001 *
#120
b11111111111111111111011111100101 !
b11111111111111111111011111100101 )
b11111111111111111111011111100101 ,
b1111011111100101 %
b1111011111100101 &
b10010 *
#125
b111001001110111 !
b111001001110111 )
b111001001110111 ,
b111001001110111 %
b111001001110111 &
b10011 *
#130
b0 !
b0 )
b0 ,
b0 %
b0 &
1$
b10100 *
#135
b1111111111111111 !
b1111111111111111 )
b1111111111111111 ,
b1111111111111111 %
b1111111111111111 &
#140
b1000000000000000 !
b1000000000000000 )
b1000000000000000 ,
b1000000000000000 %
b1000000000000000 &
#145
b1010101111001101 !
b1010101111001101 )
b1010101111001101 ,
b1010101111001101 %
b1010101111001101 &
#150
b1101011000010010 !
b1101011000010010 )
b1101011000010010 ,
b1101011000010010 %
b1101011000010010 &
#155
b1101101110001111 !
b1101101110001111 )
b1101101110001111 ,
b1101101110001111 %
b1101101110001111 &
b1 +
#160
b110100111110010 !
b110100111110010 )
b110100111110010 ,
b110100111110010 %
b110100111110010 &
b10 +
#165
b1001011011001110 !
b1001011011001110 )
b1001011011001110 ,
b1001011011001110 %
b1001011011001110 &
b11 +
#170
b111101011101000 !
b111101011101000 )
b111101011101000 ,
b111101011101000 %
b111101011101000 &
b100 +
#175
b100111011000101 !
b100111011000101 )
b100111011000101 ,
b100111011000101 %
b100111011000101 &
b101 +
#180
b100100101011100 !
b100100101011100 )
b100100101011100 ,
b100100101011100 %
b100100101011100 &
b110 +
#185
b10100010111101 !
b10100010111101 )
b10100010111101 ,
b10100010111101 %
b10100010111101 &
b111 +
#190
b101100000101101 !
b101100000101101 )
b101100000101101 ,
b101100000101101 %
b101100000101101 &
b1000 +
#195
b10011001100101 !
b10011001100101 )
b10011001100101 ,
b10011001100101 %
b10011001100101 &
b1001 +
#200
b110001001100011 !
b110001001100011 )
b110001001100011 ,
b110001001100011 %
b110001001100011 &
b1010 +
#205
b1000011100001010 !
b1000011100001010 )
b1000011100001010 ,
b1000011100001010 %
b1000011100001010 &
b1011 +
#210
b10001010000000 !
b10001010000000 )
b10001010000000 ,
b10001010000000 %
b10001010000000 &
b1100 +
#215
b10000100100000 !
b10000100100000 )
b10000100100000 ,
b10000100100000 %
b10000100100000 &
b1101 +
#220
b100010110101010 !
b100010110101010 )
b100010110101010 ,
b100010110101010 %
b100010110101010 &
b1110 +
#225
b1100110010011101 !
b1100110010011101 )
b1100110010011101 ,
b1100110010011101 %
b1100110010011101 &
b1111 +
#230
b11111010010110 !
b11111010010110 )
b11111010010110 ,
b11111010010110 %
b11111010010110 &
b10000 +
#235
b1011100000010011 !
b1011100000010011 )
b1011100000010011 ,
b1011100000010011 %
b1011100000010011 &
b10001 +
#240
b11100000001101 !
b11100000001101 )
b11100000001101 ,
b11100000001101 %
b11100000001101 &
b10010 +
#245
b1101011001010011 !
b1101011001010011 )
b1101011001010011 ,
b1101011001010011 %
b1101011001010011 &
b10011 +
#250
b10100 +
