Memory/src/bit_extender.sv
module bit_extender #(parameter WIDTH = 32, IMM_WIDTH = 16)(
    input logic EXT_Op,
    input logic[IMM_WIDTH-1:0] immediate_var,
    output logic[WIDTH-1:0] extended_var
);

always_comb begin
    if (!EXT_Op) begin
        extended_var = {{(WIDTH-IMM_WIDTH){immediate_var[IMM_WIDTH-1]}}, immediate_var};
    end else begin
        extended_var = {{(WIDTH-IMM_WIDTH){1'b0}}, immediate_var};
    end
end



endmodule

Memory/tb/bit_extender_tb.sv
module bit_extender_tb;
localparam WIDTH     = 32;
localparam IMM_WIDTH = 16;

logic                    EXT_Op;
logic [IMM_WIDTH-1:0]    immediate_var;
logic [WIDTH-1:0]        extended_var;

bit_extender #(.WIDTH(WIDTH), .IMM_WIDTH(IMM_WIDTH)) dut (
    .EXT_Op(EXT_Op),
    .immediate_var(immediate_var),
    .extended_var(extended_var)
);

int pass_count = 0;
int fail_count = 0;

task check(
    input logic [WIDTH-1:0] expected,
    input string            label
);
    #5;
    if (extended_var === expected) begin
        $display("PASS [%s] EXT_Op=%b imm=%h | extended=%h", label, EXT_Op, immediate_var, extended_var);
        pass_count++;
    end else begin
        $error("FAIL [%s] EXT_Op=%b imm=%h | expected=%h got=%h", label, EXT_Op, immediate_var, expected, extended_var);
        fail_count++;
    end
endtask

initial begin
    $dumpfile("dump/bit_extender.vcd");
    $dumpvars(0, bit_extender_tb);

    // ── Sign extend (EXT_Op = 0) — addi/lw/sw/beq/bne ───────────────────
    EXT_Op = 1'b0;
    immediate_var = 16'h0000; check(32'h00000000, "sign-extend zero");
    immediate_var = 16'hFFFF; check(32'hFFFFFFFF, "sign-extend all ones");
    immediate_var = 16'h8000; check(32'hFFFF8000, "sign-extend negative MSB set");
    immediate_var = 16'h7FFF; check(32'h00007FFF, "sign-extend max positive");
    immediate_var = 16'h0001; check(32'h00000001, "sign-extend positive one");
    immediate_var = 16'hABCD; check(32'hFFFFABCD, "sign-extend negative pattern");
    for (int i = 0; i < 20; i++) begin
        immediate_var = $urandom;
        check({{16{immediate_var[15]}}, immediate_var}, "sign-extend random");
    end

    // ── Zero extend (EXT_Op = 1) — andi/ori ─────────────────────────────
    EXT_Op = 1'b1;
    immediate_var = 16'h0000; check(32'h00000000, "zero-extend zero");
    immediate_var = 16'hFFFF; check(32'h0000FFFF, "zero-extend all ones");
    immediate_var = 16'h8000; check(32'h00008000, "zero-extend MSB set");
    immediate_var = 16'hABCD; check(32'h0000ABCD, "zero-extend pattern");
    for (int i = 0; i < 20; i++) begin
        immediate_var = $urandom;
        check({16'h0000, immediate_var}, "zero-extend random");
    end

    $display("──────────────────────────────────────────");
    $display("bit_extender testbench complete: %0d passed, %0d failed", pass_count, fail_count);
    if (fail_count == 0)
        $display("ALL TESTS PASSED");
    else
        $display("SOME TESTS FAILED — see errors above");
    $display("──────────────────────────────────────────");

    $finish;
end
endmodule

Memory/dump/bit_extender.vcd
$date
	Fri Aug 14 16:30:20 2026
$end
$version
	Icarus Verilog
$end
$timescale
	1s
$end
$scope module bit_extender_tb $end
$var wire 32 ! extended_var [31:0] $end
$var parameter 32 " IMM_WIDTH $end
$var parameter 32 # WIDTH $end
$var reg 1 $ EXT_Op $end
$var reg 16 % immediate_var [15:0] $end
$var integer 32 & fail_count [31:0] $end
$var integer 32 ' pass_count [31:0] $end
$scope module dut $end
$var wire 1 $ EXT_Op $end
$var wire 16 ( immediate_var [15:0] $end
$var parameter 32 ) IMM_WIDTH $end
$var parameter 32 * WIDTH $end
$var reg 32 + extended_var [31:0] $end
$upscope $end
$scope begin $ivl_for_loop0 $end
$var integer 32 , i [31:0] $end
$upscope $end
$scope begin $ivl_for_loop1 $end
$var integer 32 - i [31:0] $end
$upscope $end
$scope task check $end
$var reg 32 . expected [31:0] $end
$upscope $end
$upscope $end
$enddefinitions $end
$comment Show the parameter values. $end
$dumpall
b100000 *
b10000 )
b100000 #
b10000 "
$end
#0
$dumpvars
b0 .
b0 -
b0 ,
b0 +
b0 (
b0 '
b0 &
b0 %
0$
b0 !
$end
#5
b11111111111111111111111111111111 !
b11111111111111111111111111111111 +
b11111111111111111111111111111111 .
b1111111111111111 %
b1111111111111111 (
b1 '
#10
b11111111111111111000000000000000 !
b11111111111111111000000000000000 +
b11111111111111111000000000000000 .
b1000000000000000 %
b1000000000000000 (
b10 '
#15
b111111111111111 !
b111111111111111 +
b111111111111111 .
b111111111111111 %
b111111111111111 (
b11 '
#20
b1 !
b1 +
b1 .
b1 %
b1 (
b100 '
#25
b11111111111111111010101111001101 !
b11111111111111111010101111001101 +
b11111111111111111010101111001101 .
b1010101111001101 %
b1010101111001101 (
b101 '
#30
b11010100100100 !
b11010100100100 +
b11010100100100 .
b11010100100100 %
b11010100100100 (
b110 '
#35
b101111010000001 !
b101111010000001 +
b101111010000001 .
b101111010000001 %
b101111010000001 (
b1 ,
b111 '
#40
b11111111111111111101011000001001 !
b11111111111111111101011000001001 +
b11111111111111111101011000001001 .
b1101011000001001 %
b1101011000001001 (
b10 ,
b1000 '
#45
b101011001100011 !
b101011001100011 +
b101011001100011 .
b101011001100011 %
b101011001100011 (
b11 ,
b1001 '
#50
b111101100001101 !
b111101100001101 +
b111101100001101 .
b111101100001101 %
b111101100001101 (
b100 ,
b1010 '
#55
b11111111111111111001100110001101 !
b11111111111111111001100110001101 +
b11111111111111111001100110001101 .
b1001100110001101 %
b1001100110001101 (
b101 ,
b1011 '
#60
b11111111111111111000010001100101 !
b11111111111111111000010001100101 +
b11111111111111111000010001100101 .
b1000010001100101 %
b1000010001100101 (
b110 ,
b1100 '
#65
b101001000010010 !
b101001000010010 +
b101001000010010 .
b101001000010010 %
b101001000010010 (
b111 ,
b1101 '
#70
b11111111111111111110001100000001 !
b11111111111111111110001100000001 +
b11111111111111111110001100000001 .
b1110001100000001 %
b1110001100000001 (
b1000 ,
b1110 '
#75
b11111111111111111100110100001101 !
b11111111111111111100110100001101 +
b11111111111111111100110100001101 .
b1100110100001101 %
b1100110100001101 (
b1001 ,
b1111 '
#80
b11111111111111111111000101110110 !
b11111111111111111111000101110110 +
b11111111111111111111000101110110 .
b1111000101110110 %
b1111000101110110 (
b1010 ,
b10000 '
#85
b11111111111111111100110100111101 !
b11111111111111111100110100111101 +
b11111111111111111100110100111101 .
b1100110100111101 %
b1100110100111101 (
b1011 ,
b10001 '
#90
b101011111101101 !
b101011111101101 +
b101011111101101 .
b101011111101101 %
b101011111101101 (
b1100 ,
b10010 '
#95
b11111111111111111111011110001100 !
b11111111111111111111011110001100 +
b11111111111111111111011110001100 .
b1111011110001100 %
b1111011110001100 (
b1101 ,
b10011 '
#100
b11111111111111111110100111111001 !
b11111111111111111110100111111001 +
b11111111111111111110100111111001 .
b1110100111111001 %
b1110100111111001 (
b1110 ,
b10100 '
#105
b10010011000110 !
b10010011000110 +
b10010011000110 .
b10010011000110 %
b10010011000110 (
b1111 ,
b10101 '
#110
b11111111111111111000010011000101 !
b11111111111111111000010011000101 +
b11111111111111111000010011000101 .
b1000010011000101 %
b1000010011000101 (
b10000 ,
b10110 '
#115
b11111111111111111101001010101010 !
b11111111111111111101001010101010 +
b11111111111111111101001010101010 .
b1101001010101010 %
b1101001010101010 (
b10001 ,
b10111 '
#120
b11111111111111111111011111100101 !
b11111111111111111111011111100101 +
b11111111111111111111011111100101 .
b1111011111100101 %
b1111011111100101 (
b10010 ,
b11000 '
#125
b111001001110111 !
b111001001110111 +
b111001001110111 .
b111001001110111 %
b111001001110111 (
b10011 ,
b11001 '
#130
b0 !
b0 +
b0 .
b0 %
b0 (
1$
b10100 ,
b11010 '
#135
b1111111111111111 !
b1111111111111111 +
b1111111111111111 .
b1111111111111111 %
b1111111111111111 (
b11011 '
#140
b1000000000000000 !
b1000000000000000 +
b1000000000000000 .
b1000000000000000 %
b1000000000000000 (
b11100 '
#145
b1010101111001101 !
b1010101111001101 +
b1010101111001101 .
b1010101111001101 %
b1010101111001101 (
b11101 '
#150
b1101011000010010 !
b1101011000010010 +
b1101011000010010 .
b1101011000010010 %
b1101011000010010 (
b11110 '
#155
b1101101110001111 !
b1101101110001111 +
b1101101110001111 .
b1101101110001111 %
b1101101110001111 (
b1 -
b11111 '
#160
b110100111110010 !
b110100111110010 +
b110100111110010 .
b110100111110010 %
b110100111110010 (
b10 -
b100000 '
#165
b1001011011001110 !
b1001011011001110 +
b1001011011001110 .
b1001011011001110 %
b1001011011001110 (
b11 -
b100001 '
#170
b111101011101000 !
b111101011101000 +
b111101011101000 .
b111101011101000 %
b111101011101000 (
b100 -
b100010 '
#175
b100111011000101 !
b100111011000101 +
b100111011000101 .
b100111011000101 %
b100111011000101 (
b101 -
b100011 '
#180
b100100101011100 !
b100100101011100 +
b100100101011100 .
b100100101011100 %
b100100101011100 (
b110 -
b100100 '
#185
b10100010111101 !
b10100010111101 +
b10100010111101 .
b10100010111101 %
b10100010111101 (
b111 -
b100101 '
#190
b101100000101101 !
b101100000101101 +
b101100000101101 .
b101100000101101 %
b101100000101101 (
b1000 -
b100110 '
#195
b10011001100101 !
b10011001100101 +
b10011001100101 .
b10011001100101 %
b10011001100101 (
b1001 -
b100111 '
#200
b110001001100011 !
b110001001100011 +
b110001001100011 .
b110001001100011 %
b110001001100011 (
b1010 -
b101000 '
#205
b1000011100001010 !
b1000011100001010 +
b1000011100001010 .
b1000011100001010 %
b1000011100001010 (
b1011 -
b101001 '
#210
b10001010000000 !
b10001010000000 +
b10001010000000 .
b10001010000000 %
b10001010000000 (
b1100 -
b101010 '
#215
b10000100100000 !
b10000100100000 +
b10000100100000 .
b10000100100000 %
b10000100100000 (
b1101 -
b101011 '
#220
b100010110101010 !
b100010110101010 +
b100010110101010 .
b100010110101010 %
b100010110101010 (
b1110 -
b101100 '
#225
b1100110010011101 !
b1100110010011101 +
b1100110010011101 .
b1100110010011101 %
b1100110010011101 (
b1111 -
b101101 '
#230
b11111010010110 !
b11111010010110 +
b11111010010110 .
b11111010010110 %
b11111010010110 (
b10000 -
b101110 '
#235
b1011100000010011 !
b1011100000010011 +
b1011100000010011 .
b1011100000010011 %
b1011100000010011 (
b10001 -
b101111 '
#240
b11100000001101 !
b11100000001101 +
b11100000001101 .
b11100000001101 %
b11100000001101 (
b10010 -
b110000 '
#245
b1101011001010011 !
b1101011001010011 +
b1101011001010011 .
b1101011001010011 %
b1101011001010011 (
b10011 -
b110001 '
#250
b10100 -
b110010 '
