Memory/src/bit_extender.sv
module bit_extender #(parameter WIDTH = 32, IMM_WIDTH = 16)(
    input logic[IMM_WIDTH-1:0] immediate_var,
    output logic[WIDTH-1:0] extended_var
);


always_comb begin : bit_extender

    extended_var[WIDTH-1:IMM_WIDTH] = immediate_var[IMM_WIDTH-1];
    extended_var[IMM_WIDTH-1:0]=immediate_var[IMM_WIDTH-1:0];
end
endmodule

Memory/tb/bit_extender_tb.sv
module bit_extender_tb;
localparam WIDTH     = 32;
localparam IMM_WIDTH = 16;

logic [IMM_WIDTH-1:0]    immediate_var;
logic [WIDTH-1:0]        extended_var;

bit_extender #(.WIDTH(WIDTH), .IMM_WIDTH(IMM_WIDTH)) dut (
    .immediate_var(immediate_var),
    .extended_var(extended_var)
);

task check(
    input logic [WIDTH-1:0] expected,
    input string            label
);
    #5;
    if (extended_var === expected)
        $display("PASS [%s] imm=%h | extended=%h", label, immediate_var, extended_var);
    else
        $error("FAIL [%s] imm=%h | expected=%h got=%h", label, immediate_var, expected, extended_var);
endtask

initial begin
    $dumpfile("dump/bit_extender.vcd");
    $dumpvars(0, bit_extender_tb);

    // ── Sign extend (the module's only mode) ───────────────────────────
    immediate_var = 16'h0000; check(32'h00000000, "sign-extend zero");
    immediate_var = 16'hFFFF; check(32'hFFFFFFFF, "sign-extend all ones");
    immediate_var = 16'h8000; check(32'hFFFF8000, "sign-extend negative MSB set");
    immediate_var = 16'h7FFF; check(32'h00007FFF, "sign-extend max positive");
    immediate_var = 16'h0001; check(32'h00000001, "sign-extend positive one");
    immediate_var = 16'hABCD; check(32'hFFFFABCD, "sign-extend negative pattern");
    for (int i = 0; i < 20; i++) begin
        immediate_var = $urandom;
        check({{16{immediate_var[15]}}, immediate_var}, "sign-extend random");
    end

    $display("All bit_extender tests complete");
    $finish;
end
endmodule

Memory/dump/bit_extender.vcd
$date
	Fri Aug 14 11:42:00 2026
$end
$version
	Icarus Verilog
$end
$timescale
	1s
$end
$scope module bit_extender_tb $end
$var wire 32 ! extended_var [31:0] $end
$var parameter 32 " IMM_WIDTH $end
$var parameter 32 # WIDTH $end
$var reg 16 $ immediate_var [15:0] $end
$scope module dut $end
$var wire 16 % immediate_var [15:0] $end
$var wire 32 & extended_var [31:0] $end
$var parameter 32 ' IMM_WIDTH $end
$var parameter 32 ( WIDTH $end
$upscope $end
$scope begin $ivl_for_loop0 $end
$var integer 32 ) i [31:0] $end
$upscope $end
$scope task check $end
$var reg 32 * expected [31:0] $end
$upscope $end
$upscope $end
$enddefinitions $end
$comment Show the parameter values. $end
$dumpall
b100000 (
b10000 '
b100000 #
b10000 "
$end
#0
$dumpvars
b0 *
b0 )
b0 &
b0 %
b0 $
b0 !
$end
#5
b11111111111111111111111111111111 *
b11111111111111111111111111111111 !
b11111111111111111111111111111111 &
b1111111111111111 $
b1111111111111111 %
#10
b11111111111111111000000000000000 *
b11111111111111111000000000000000 !
b11111111111111111000000000000000 &
b1000000000000000 $
b1000000000000000 %
#15
b111111111111111 *
b111111111111111 !
b111111111111111 &
b111111111111111 $
b111111111111111 %
#20
b1 *
b1 !
b1 &
b1 $
b1 %
#25
b11111111111111111010101111001101 *
b11111111111111111010101111001101 !
b11111111111111111010101111001101 &
b1010101111001101 $
b1010101111001101 %
#30
b11010100100100 *
b11010100100100 !
b11010100100100 &
b11010100100100 $
b11010100100100 %
#35
b101111010000001 *
b101111010000001 !
b101111010000001 &
b101111010000001 $
b101111010000001 %
b1 )
#40
b11111111111111111101011000001001 *
b11111111111111111101011000001001 !
b11111111111111111101011000001001 &
b1101011000001001 $
b1101011000001001 %
b10 )
#45
b101011001100011 *
b101011001100011 !
b101011001100011 &
b101011001100011 $
b101011001100011 %
b11 )
#50
b111101100001101 *
b111101100001101 !
b111101100001101 &
b111101100001101 $
b111101100001101 %
b100 )
#55
b11111111111111111001100110001101 *
b11111111111111111001100110001101 !
b11111111111111111001100110001101 &
b1001100110001101 $
b1001100110001101 %
b101 )
#60
b11111111111111111000010001100101 *
b11111111111111111000010001100101 !
b11111111111111111000010001100101 &
b1000010001100101 $
b1000010001100101 %
b110 )
#65
b101001000010010 *
b101001000010010 !
b101001000010010 &
b101001000010010 $
b101001000010010 %
b111 )
#70
b11111111111111111110001100000001 *
b11111111111111111110001100000001 !
b11111111111111111110001100000001 &
b1110001100000001 $
b1110001100000001 %
b1000 )
#75
b11111111111111111100110100001101 *
b11111111111111111100110100001101 !
b11111111111111111100110100001101 &
b1100110100001101 $
b1100110100001101 %
b1001 )
#80
b11111111111111111111000101110110 *
b11111111111111111111000101110110 !
b11111111111111111111000101110110 &
b1111000101110110 $
b1111000101110110 %
b1010 )
#85
b11111111111111111100110100111101 *
b11111111111111111100110100111101 !
b11111111111111111100110100111101 &
b1100110100111101 $
b1100110100111101 %
b1011 )
#90
b101011111101101 *
b101011111101101 !
b101011111101101 &
b101011111101101 $
b101011111101101 %
b1100 )
#95
b11111111111111111111011110001100 *
b11111111111111111111011110001100 !
b11111111111111111111011110001100 &
b1111011110001100 $
b1111011110001100 %
b1101 )
#100
b11111111111111111110100111111001 *
b11111111111111111110100111111001 !
b11111111111111111110100111111001 &
b1110100111111001 $
b1110100111111001 %
b1110 )
#105
b10010011000110 *
b10010011000110 !
b10010011000110 &
b10010011000110 $
b10010011000110 %
b1111 )
#110
b11111111111111111000010011000101 *
b11111111111111111000010011000101 !
b11111111111111111000010011000101 &
b1000010011000101 $
b1000010011000101 %
b10000 )
#115
b11111111111111111101001010101010 *
b11111111111111111101001010101010 !
b11111111111111111101001010101010 &
b1101001010101010 $
b1101001010101010 %
b10001 )
#120
b11111111111111111111011111100101 *
b11111111111111111111011111100101 !
b11111111111111111111011111100101 &
b1111011111100101 $
b1111011111100101 %
b10010 )
#125
b111001001110111 *
b111001001110111 !
b111001001110111 &
b111001001110111 $
b111001001110111 %
b10011 )
#130
b10100 )
